MANIFEST.in
README.rst
requirements.txt
setup.py
configcascade/__init__.py
configcascade.egg-info/PKG-INFO
configcascade.egg-info/SOURCES.txt
configcascade.egg-info/dependency_links.txt
configcascade.egg-info/not-zip-safe
configcascade.egg-info/requires.txt
configcascade.egg-info/top_level.txt