Metadata-Version: 1.0
Name: configcascade
Version: 1.0.0
Summary: A simple Configuration System which allows you to import and override or merge configuration parameters
Home-page: https://github.com/felixcarmona/configcascade
Author: Felix Carmona
Author-email: mail@felixcarmona.com
License: UNKNOWN
Platform: UNKNOWN
